boring/__init__.py
boring/client.py
boring/config.py
boring/main.py
boring/version_check.py
boring/commands/__init__.py
boring/commands/download.py
boring/commands/sections.py
boring/commands/setup.py
boring/commands/solve.py
boring/commands/status.py
boring/commands/update.py
boring_cli-0.1.6.dist-info/METADATA
boring_cli-0.1.6.dist-info/WHEEL
boring_cli-0.1.6.dist-info/entry_points.txt
boring_cli-0.1.6.dist-info/licenses/LICENSE
boring_cli-0.1.6.dist-info/RECORD
