Metadata-Version: 2.4
Name: boring-cli
Version: 0.1.6
Summary: CLI tool for managing Lark Suite tasks
Project-URL: Homepage, https://github.com/anhbinhnguyen/boring-cli
Project-URL: Repository, https://github.com/anhbinhnguyen/boring-cli
Project-URL: Issues, https://github.com/anhbinhnguyen/boring-cli/issues
Author: Boring Agents Team
License-Expression: MIT
License-File: LICENSE
Keywords: cli,lark,productivity,tasks
Classifier: Development Status :: 4 - Beta
Classifier: Environment :: Console
Classifier: Intended Audience :: Developers
Classifier: License :: OSI Approved :: MIT License
Classifier: Operating System :: OS Independent
Classifier: Programming Language :: Python :: 3
Classifier: Programming Language :: Python :: 3.9
Classifier: Programming Language :: Python :: 3.10
Classifier: Programming Language :: Python :: 3.11
Classifier: Programming Language :: Python :: 3.12
Classifier: Topic :: Utilities
Requires-Python: >=3.9
Requires-Dist: click>=8.0.0
Requires-Dist: httpx>=0.26.0
Requires-Dist: packaging>=21.0
Requires-Dist: pyyaml>=6.0
Requires-Dist: rich>=13.0.0
Provides-Extra: dev
Requires-Dist: black>=23.0.0; extra == 'dev'
Requires-Dist: pytest-cov>=4.0.0; extra == 'dev'
Requires-Dist: pytest>=7.0.0; extra == 'dev'
Requires-Dist: ruff>=0.1.0; extra == 'dev'
